remote_drawing_provider/__init__.py
remote_drawing_provider/logger.py
remote_drawing_provider/provider.py
remote_drawing_provider-1.0.4.dist-info/LICENSE
remote_drawing_provider-1.0.4.dist-info/METADATA
remote_drawing_provider-1.0.4.dist-info/WHEEL
remote_drawing_provider-1.0.4.dist-info/top_level.txt
remote_drawing_provider-1.0.4.dist-info/RECORD
