Metadata-Version: 2.1
Name: remote-drawing-provider
Version: 1.0.4
Summary: Remote Drawing Provider
Home-page: https://github.com/XiaoyanQian/remote-drawing
Author: XY-qian
Author-email: XiaoyanQian <xiaoyanqian1010@gmail.com>
Project-URL: Homepage, https://github.com/XiaoyanQian/remote-drawing
Project-URL: Bug Tracker, https://github.com/XiaoyanQian/remote-drawing/issues
Platform: any
Classifier: Programming Language :: Python :: 3
Classifier: License :: OSI Approved :: MIT License
Requires-Python: >=3.7
License-File: LICENSE
Requires-Dist: numpy
Requires-Dist: torch
Requires-Dist: colorama (>=0.4.6)
Requires-Dist: websockets (>=11.0.2)
